odoo/addons/l10n_cl_etd/README.rst
odoo/addons/l10n_cl_etd/__init__.py
odoo/addons/l10n_cl_etd/__manifest__.py
odoo/addons/l10n_cl_etd/data/backend.acp.csv
odoo/addons/l10n_cl_etd/data/res.country.csv
odoo/addons/l10n_cl_etd/i18n/es.po
odoo/addons/l10n_cl_etd/i18n/es_CL.po
odoo/addons/l10n_cl_etd/i18n/l10n_cl_etd.pot
odoo/addons/l10n_cl_etd/models/__init__.py
odoo/addons/l10n_cl_etd/models/etd_mixin.py
odoo/addons/l10n_cl_etd/models/res_company.py
odoo/addons/l10n_cl_etd/readme/CONTRIBUTORS.rst
odoo/addons/l10n_cl_etd/readme/DESCRIPTION.rst
odoo/addons/l10n_cl_etd/readme/USAGE.rst
odoo/addons/l10n_cl_etd/static/description/icon.png
odoo/addons/l10n_cl_etd/static/description/index.html
odoo12_addon_l10n_cl_etd-12.0.1.1.0.dist-info/METADATA
odoo12_addon_l10n_cl_etd-12.0.1.1.0.dist-info/WHEEL
odoo12_addon_l10n_cl_etd-12.0.1.1.0.dist-info/top_level.txt
odoo12_addon_l10n_cl_etd-12.0.1.1.0.dist-info/RECORD
